histeqkit/__init__.py
histeqkit/accuracyMeasure.py
histeqkit/algorithms.py
histeqkit/histogram.py
histeqkit/main.py
histeqkit/utils.py
histeqkit-0.0.6.dist-info/LICENSE
histeqkit-0.0.6.dist-info/METADATA
histeqkit-0.0.6.dist-info/WHEEL
histeqkit-0.0.6.dist-info/top_level.txt
histeqkit-0.0.6.dist-info/RECORD
