Metadata-Version: 2.1
Name: histeqkit
Version: 0.0.6
Summary: package for histogram equalization algorithms and image accuracy measures.
Home-page: https://github.com/pypa/sampleproject
Author: Aditya Raj
Author-email: aditya2134.ar@gmail.com
Project-URL: Bug Tracker, https://github.com/pypa/sampleproject/issues
Classifier: Programming Language :: Python :: 3
Classifier: License :: OSI Approved :: MIT License
Classifier: Operating System :: OS Independent
Requires-Python: >=3.6
License-File: LICENSE
